[
  {
    "imgSrc": "../../images/userface1.jpg",
    "imgTitle": "美女生活照1",
    "time": "2018-10-16 12:23"
  },
  {
    "imgSrc": "../../images/userface2.jpg",
    "imgTitle": "美女生活照2",
    "time": "2018-10-16 12:23"
  },
  {
    "imgSrc": "../../images/userface3.jpg",
    "imgTitle": "美女生活照3",
    "time": "2018-10-16 12:23"
  },
  {
    "imgSrc": "../../images/userface4.jpg",
    "imgTitle": "美女生活照4",
    "time": "2018-10-16 12:23"
  },
  {
    "imgSrc": "../../images/userface5.jpg",
    "imgTitle": "美女生活照5",
    "time": "2018-10-16 12:23"
  },
  {
    "imgSrc": "../../images/userface1.jpg",
    "imgTitle": "美女生活照6",
    "time": "2018-10-16 12:23"
  },
  {
    "imgSrc": "../../images/userface2.jpg",
    "imgTitle": "美女生活照7",
    "time": "2018-10-16 12:23"
  },
  {
    "imgSrc": "../../images/userface3.jpg",
    "imgTitle": "美女生活照8",
    "time": "2018-10-16 12:23"
  },
  {
    "imgSrc": "../../images/userface4.jpg",
    "imgTitle": "美女生活照9",
    "time": "2018-10-16 12:23"
  },
  {
    "imgSrc": "../../images/userface5.jpg",
    "imgTitle": "美女生活照10",
    "time": "2018-10-16 12:23"
  },
  {
    "imgSrc": "../../images/userface1.jpg",
    "imgTitle": "美女生活照11",
    "time": "2018-10-16 12:23"
  },
  {
    "imgSrc": "../../images/userface2.jpg",
    "imgTitle": "美女生活照12",
    "time": "2018-10-16 12:23"
  },
  {
    "imgSrc": "../../images/userface3.jpg",
    "imgTitle": "美女生活照13",
    "time": "2018-10-16 12:23"
  },
  {
    "imgSrc": "../../images/userface4.jpg",
    "imgTitle": "美女生活照14",
    "time": "2018-10-16 12:23"
  },
  {
    "imgSrc": "../../images/userface5.jpg",
    "imgTitle": "美女生活照15",
    "time": "2018-10-16 12:23"
  },
  {
    "imgSrc": "../../images/userface1.jpg",
    "imgTitle": "美女生活照16",
    "time": "2018-10-16 12:23"
  },
  {
    "imgSrc": "../../images/userface2.jpg",
    "imgTitle": "美女生活照17",
    "time": "2018-10-16 12:23"
  },
  {
    "imgSrc": "../../images/userface3.jpg",
    "imgTitle": "美女生活照18"
  },
  {
    "imgSrc": "../../images/userface4.jpg",
    "imgTitle": "美女生活照19",
    "time": "2018-10-16 12:23"
  },
  {
    "imgSrc": "../../images/userface5.jpg",
    "imgTitle": "美女生活照20",
    "time": "2018-10-16 12:23"
  },
  {
    "imgSrc": "../../images/userface1.jpg",
    "imgTitle": "美女生活照21",
    "time": "2018-10-16 12:23"
  },
  {
    "imgSrc": "../../images/userface2.jpg",
    "imgTitle": "美女生活照22",
    "time": "2018-10-16 12:23"
  },
  {
    "imgSrc": "../../images/userface3.jpg",
    "imgTitle": "美女生活照23",
    "time": "2018-10-16 12:23"
  },
  {
    "imgSrc": "../../images/userface4.jpg",
    "imgTitle": "美女生活照24",
    "time": "2018-10-16 12:23"
  },
  {
    "imgSrc": "../../images/userface5.jpg",
    "imgTitle": "美女生活照25",
    "time": "2018-10-16 12:23"
  },
  {
    "imgSrc": "../../images/userface1.jpg",
    "imgTitle": "美女生活照26",
    "time": "2018-10-16 12:23"
  },
  {
    "imgSrc": "../../images/userface2.jpg",
    "imgTitle": "美女生活照27",
    "time": "2018-10-16 12:23"
  },
  {
    "imgSrc": "../../images/userface3.jpg",
    "imgTitle": "美女生活照28",
    "time": "2018-10-16 12:23"
  },
  {
    "imgSrc": "../../images/userface4.jpg",
    "imgTitle": "美女生活照29",
    "time": "2018-10-16 12:23"
  },
  {
    "imgSrc": "../../images/userface5.jpg",
    "imgTitle": "美女生活照30",
    "time": "2018-10-16 12:23"
  },
  {
    "imgSrc": "../../images/userface3.jpg",
    "imgTitle": "美女生活照31",
    "time": "2018-10-16 12:23"
  }
]